pyEstradasPT/__init__.py
pyEstradasPT/api.py
pyEstradasPT/cameras.py
pyEstradasPT/consts.py
pyEstradasPT-1.0.2.dist-info/LICENSE
pyEstradasPT-1.0.2.dist-info/METADATA
pyEstradasPT-1.0.2.dist-info/WHEEL
pyEstradasPT-1.0.2.dist-info/top_level.txt
pyEstradasPT-1.0.2.dist-info/zip-safe
pyEstradasPT-1.0.2.dist-info/RECORD
